{
  "exported_at": "2026-03-29T04:54:41.494Z",
  "source": "api",
  "page_url": "https://platform.worldquantbrain.com/data/data-sets/news21?delay=1&instrumentType=EQUITY&limit=20&offset=0&region=EUR&universe=TOP2500",
  "total_count": 47,
  "row_count": 47,
  "page_count": 3,
  "pages": [
    {
      "page": 1,
      "offset": 0,
      "item_count": 20,
      "new_item_count": 20,
      "item_path": "results",
      "api_url": "https://api.worldquantbrain.com/data-fields?delay=1&instrumentType=EQUITY&limit=20&offset=0&region=EUR&universe=TOP2500&dataset.id=news21"
    },
    {
      "page": 2,
      "offset": 20,
      "item_count": 20,
      "new_item_count": 20,
      "item_path": "results",
      "api_url": "https://api.worldquantbrain.com/data-fields?delay=1&instrumentType=EQUITY&limit=20&offset=20&region=EUR&universe=TOP2500&dataset.id=news21"
    },
    {
      "page": 3,
      "offset": 40,
      "item_count": 7,
      "new_item_count": 7,
      "item_path": "results",
      "api_url": "https://api.worldquantbrain.com/data-fields?delay=1&instrumentType=EQUITY&limit=20&offset=40&region=EUR&universe=TOP2500&dataset.id=news21"
    }
  ],
  "rows": [
    {
      "id": "earning_broker_count",
      "description": "Number of brokers contributing to the earnings consensus for the event.",
      "dataset": {
        "id": "news21",
        "name": "Macro Economic Event Data"
      },
      "category": {
        "id": "news",
        "name": "News"
      },
      "subcategory": {
        "id": "news-news",
        "name": "News"
      },
      "region": "EUR",
      "delay": 1,
      "universe": "TOP2500",
      "type": "VECTOR",
      "dateCoverage": 1,
      "coverage": 0.6194,
      "userCount": 1,
      "alphaCount": 1,
      "pyramidMultiplier": 1.5,
      "themes": []
    },
    {
      "id": "earning_calendar_quarter_end",
      "description": "The end date of the calendar quarter associated with the earnings event.",
      "dataset": {
        "id": "news21",
        "name": "Macro Economic Event Data"
      },
      "category": {
        "id": "news",
        "name": "News"
      },
      "subcategory": {
        "id": "news-news",
        "name": "News"
      },
      "region": "EUR",
      "delay": 1,
      "universe": "TOP2500",
      "type": "VECTOR",
      "dateCoverage": 1,
      "coverage": 0.6194,
      "userCount": 0,
      "alphaCount": 0,
      "pyramidMultiplier": 1.5,
      "themes": []
    },
    {
      "id": "earning_event_type_label",
      "description": "Descriptive label for the type of earnings event (e.g., actual, estimate).",
      "dataset": {
        "id": "news21",
        "name": "Macro Economic Event Data"
      },
      "category": {
        "id": "news",
        "name": "News"
      },
      "subcategory": {
        "id": "news-news",
        "name": "News"
      },
      "region": "EUR",
      "delay": 1,
      "universe": "TOP2500",
      "type": "VECTOR",
      "dateCoverage": 1,
      "coverage": 0.6194,
      "userCount": 1,
      "alphaCount": 1,
      "pyramidMultiplier": 1.5,
      "themes": []
    },
    {
      "id": "earning_fiscal_quarter_number",
      "description": "The fiscal quarter number (e.g., 1, 2, 3, 4) for the earnings event.",
      "dataset": {
        "id": "news21",
        "name": "Macro Economic Event Data"
      },
      "category": {
        "id": "news",
        "name": "News"
      },
      "subcategory": {
        "id": "news-news",
        "name": "News"
      },
      "region": "EUR",
      "delay": 1,
      "universe": "TOP2500",
      "type": "VECTOR",
      "dateCoverage": 1,
      "coverage": 0.6194,
      "userCount": 0,
      "alphaCount": 0,
      "pyramidMultiplier": 1.5,
      "themes": []
    },
    {
      "id": "earning_fiscal_year",
      "description": "The fiscal year for which the earnings event is reported.",
      "dataset": {
        "id": "news21",
        "name": "Macro Economic Event Data"
      },
      "category": {
        "id": "news",
        "name": "News"
      },
      "subcategory": {
        "id": "news-news",
        "name": "News"
      },
      "region": "EUR",
      "delay": 1,
      "universe": "TOP2500",
      "type": "VECTOR",
      "dateCoverage": 1,
      "coverage": 0.6194,
      "userCount": 0,
      "alphaCount": 0,
      "pyramidMultiplier": 1.5,
      "themes": []
    },
    {
      "id": "earning_fiscal_year_end",
      "description": "The fiscal year end date associated with the earnings event.",
      "dataset": {
        "id": "news21",
        "name": "Macro Economic Event Data"
      },
      "category": {
        "id": "news",
        "name": "News"
      },
      "subcategory": {
        "id": "news-news",
        "name": "News"
      },
      "region": "EUR",
      "delay": 1,
      "universe": "TOP2500",
      "type": "VECTOR",
      "dateCoverage": 1,
      "coverage": 0.6194,
      "userCount": 0,
      "alphaCount": 0,
      "pyramidMultiplier": 1.5,
      "themes": []
    },
    {
      "id": "earning_number_value",
      "description": "The reported or estimated earnings number (e.g., EPS) for the event.",
      "dataset": {
        "id": "news21",
        "name": "Macro Economic Event Data"
      },
      "category": {
        "id": "news",
        "name": "News"
      },
      "subcategory": {
        "id": "news-news",
        "name": "News"
      },
      "region": "EUR",
      "delay": 1,
      "universe": "TOP2500",
      "type": "VECTOR",
      "dateCoverage": 1,
      "coverage": 0.6194,
      "userCount": 0,
      "alphaCount": 0,
      "pyramidMultiplier": 1.5,
      "themes": []
    },
    {
      "id": "earning_time_type",
      "description": "Classification of the time associated with the earnings event (e.g., before open, after close).",
      "dataset": {
        "id": "news21",
        "name": "Macro Economic Event Data"
      },
      "category": {
        "id": "news",
        "name": "News"
      },
      "subcategory": {
        "id": "news-news",
        "name": "News"
      },
      "region": "EUR",
      "delay": 1,
      "universe": "TOP2500",
      "type": "VECTOR",
      "dateCoverage": 1,
      "coverage": 0.6194,
      "userCount": 1,
      "alphaCount": 1,
      "pyramidMultiplier": 1.5,
      "themes": []
    },
    {
      "id": "estimated_next_shareholder_meeting_date",
      "description": "Estimated date for the next annual shareholder meeting, if not yet confirmed.",
      "dataset": {
        "id": "news21",
        "name": "Macro Economic Event Data"
      },
      "category": {
        "id": "news",
        "name": "News"
      },
      "subcategory": {
        "id": "news-news",
        "name": "News"
      },
      "region": "EUR",
      "delay": 1,
      "universe": "TOP2500",
      "type": "MATRIX",
      "dateCoverage": 1,
      "coverage": 0.7078,
      "userCount": 3,
      "alphaCount": 3,
      "pyramidMultiplier": 1.5,
      "themes": []
    },
    {
      "id": "event_category_label_1",
      "description": "The classification or type of the event (version 1).",
      "dataset": {
        "id": "news21",
        "name": "Macro Economic Event Data"
      },
      "category": {
        "id": "news",
        "name": "News"
      },
      "subcategory": {
        "id": "news-news",
        "name": "News"
      },
      "region": "EUR",
      "delay": 1,
      "universe": "TOP2500",
      "type": "VECTOR",
      "dateCoverage": 1,
      "coverage": 0.4169,
      "userCount": 3,
      "alphaCount": 4,
      "pyramidMultiplier": 1.5,
      "themes": []
    },
    {
      "id": "event_end_date_is_estimated",
      "description": "Boolean flag indicating if the event end date is an estimate.",
      "dataset": {
        "id": "news21",
        "name": "Macro Economic Event Data"
      },
      "category": {
        "id": "news",
        "name": "News"
      },
      "subcategory": {
        "id": "news-news",
        "name": "News"
      },
      "region": "EUR",
      "delay": 1,
      "universe": "TOP2500",
      "type": "VECTOR",
      "dateCoverage": 1,
      "coverage": 0.6194,
      "userCount": 0,
      "alphaCount": 0,
      "pyramidMultiplier": 1.5,
      "themes": []
    },
    {
      "id": "event_end_date_type",
      "description": "Type or classification of the event's end date (e.g., actual, estimated).",
      "dataset": {
        "id": "news21",
        "name": "Macro Economic Event Data"
      },
      "category": {
        "id": "news",
        "name": "News"
      },
      "subcategory": {
        "id": "news-news",
        "name": "News"
      },
      "region": "EUR",
      "delay": 1,
      "universe": "TOP2500",
      "type": "VECTOR",
      "dateCoverage": 1,
      "coverage": 0.6194,
      "userCount": 1,
      "alphaCount": 1,
      "pyramidMultiplier": 1.5,
      "themes": []
    },
    {
      "id": "event_end_time",
      "description": "The time of day when the event or reporting period ends.",
      "dataset": {
        "id": "news21",
        "name": "Macro Economic Event Data"
      },
      "category": {
        "id": "news",
        "name": "News"
      },
      "subcategory": {
        "id": "news-news",
        "name": "News"
      },
      "region": "EUR",
      "delay": 1,
      "universe": "TOP2500",
      "type": "VECTOR",
      "dateCoverage": 1,
      "coverage": 0.6194,
      "userCount": 0,
      "alphaCount": 0,
      "pyramidMultiplier": 1.5,
      "themes": []
    },
    {
      "id": "event_fiscal_year",
      "description": "The fiscal year associated with the earnings event.",
      "dataset": {
        "id": "news21",
        "name": "Macro Economic Event Data"
      },
      "category": {
        "id": "news",
        "name": "News"
      },
      "subcategory": {
        "id": "news-news",
        "name": "News"
      },
      "region": "EUR",
      "delay": 1,
      "universe": "TOP2500",
      "type": "VECTOR",
      "dateCoverage": 1,
      "coverage": 0.6194,
      "userCount": 1,
      "alphaCount": 1,
      "pyramidMultiplier": 1.5,
      "themes": []
    },
    {
      "id": "event_frequency_label",
      "description": "Label or code indicating the frequency of the event (e.g., annual, quarterly, ad hoc).",
      "dataset": {
        "id": "news21",
        "name": "Macro Economic Event Data"
      },
      "category": {
        "id": "news",
        "name": "News"
      },
      "subcategory": {
        "id": "news-news",
        "name": "News"
      },
      "region": "EUR",
      "delay": 1,
      "universe": "TOP2500",
      "type": "MATRIX",
      "dateCoverage": 1,
      "coverage": 0.4146,
      "userCount": 3,
      "alphaCount": 3,
      "pyramidMultiplier": 1.5,
      "themes": []
    },
    {
      "id": "event_quarter_label",
      "description": "Label or code indicating the quarter associated with the event (e.g., Q1, Q2).",
      "dataset": {
        "id": "news21",
        "name": "Macro Economic Event Data"
      },
      "category": {
        "id": "news",
        "name": "News"
      },
      "subcategory": {
        "id": "news-news",
        "name": "News"
      },
      "region": "EUR",
      "delay": 1,
      "universe": "TOP2500",
      "type": "VECTOR",
      "dateCoverage": 1,
      "coverage": 0.6194,
      "userCount": 0,
      "alphaCount": 0,
      "pyramidMultiplier": 1.5,
      "themes": []
    },
    {
      "id": "event_start_date_is_estimated",
      "description": "Boolean flag indicating if the event start date is an estimate.",
      "dataset": {
        "id": "news21",
        "name": "Macro Economic Event Data"
      },
      "category": {
        "id": "news",
        "name": "News"
      },
      "subcategory": {
        "id": "news-news",
        "name": "News"
      },
      "region": "EUR",
      "delay": 1,
      "universe": "TOP2500",
      "type": "VECTOR",
      "dateCoverage": 1,
      "coverage": 0.6194,
      "userCount": 0,
      "alphaCount": 0,
      "pyramidMultiplier": 1.5,
      "themes": []
    },
    {
      "id": "event_start_date_type",
      "description": "Type or classification of the event's start date (e.g., actual, estimated).",
      "dataset": {
        "id": "news21",
        "name": "Macro Economic Event Data"
      },
      "category": {
        "id": "news",
        "name": "News"
      },
      "subcategory": {
        "id": "news-news",
        "name": "News"
      },
      "region": "EUR",
      "delay": 1,
      "universe": "TOP2500",
      "type": "VECTOR",
      "dateCoverage": 1,
      "coverage": 0.6194,
      "userCount": 0,
      "alphaCount": 0,
      "pyramidMultiplier": 1.5,
      "themes": []
    },
    {
      "id": "event_start_time_2",
      "description": "The time of day when the event or reporting period begins.",
      "dataset": {
        "id": "news21",
        "name": "Macro Economic Event Data"
      },
      "category": {
        "id": "news",
        "name": "News"
      },
      "subcategory": {
        "id": "news-news",
        "name": "News"
      },
      "region": "EUR",
      "delay": 1,
      "universe": "TOP2500",
      "type": "VECTOR",
      "dateCoverage": 1,
      "coverage": 0.6194,
      "userCount": 3,
      "alphaCount": 3,
      "pyramidMultiplier": 1.5,
      "themes": []
    },
    {
      "id": "event_transcript_negative_score",
      "description": "A numeric value representing the degree of negative sentiment in an event transcript.",
      "dataset": {
        "id": "news21",
        "name": "Macro Economic Event Data"
      },
      "category": {
        "id": "news",
        "name": "News"
      },
      "subcategory": {
        "id": "news-news",
        "name": "News"
      },
      "region": "EUR",
      "delay": 1,
      "universe": "TOP2500",
      "type": "MATRIX",
      "dateCoverage": 1,
      "coverage": 0.5102,
      "userCount": 3,
      "alphaCount": 3,
      "pyramidMultiplier": 1.5,
      "themes": []
    },
    {
      "id": "event_transcript_negative_word_count",
      "description": "The count of negative words identified in an event transcript.",
      "dataset": {
        "id": "news21",
        "name": "Macro Economic Event Data"
      },
      "category": {
        "id": "news",
        "name": "News"
      },
      "subcategory": {
        "id": "news-news",
        "name": "News"
      },
      "region": "EUR",
      "delay": 1,
      "universe": "TOP2500",
      "type": "MATRIX",
      "dateCoverage": 1,
      "coverage": 0.5102,
      "userCount": 1,
      "alphaCount": 1,
      "pyramidMultiplier": 1.5,
      "themes": []
    },
    {
      "id": "event_transcript_positive_score",
      "description": "A numeric value representing the degree of positive sentiment in an event transcript.",
      "dataset": {
        "id": "news21",
        "name": "Macro Economic Event Data"
      },
      "category": {
        "id": "news",
        "name": "News"
      },
      "subcategory": {
        "id": "news-news",
        "name": "News"
      },
      "region": "EUR",
      "delay": 1,
      "universe": "TOP2500",
      "type": "MATRIX",
      "dateCoverage": 1,
      "coverage": 0.5102,
      "userCount": 4,
      "alphaCount": 4,
      "pyramidMultiplier": 1.5,
      "themes": []
    },
    {
      "id": "event_transcript_positive_word_count",
      "description": "The count of positive words identified in an event transcript.",
      "dataset": {
        "id": "news21",
        "name": "Macro Economic Event Data"
      },
      "category": {
        "id": "news",
        "name": "News"
      },
      "subcategory": {
        "id": "news-news",
        "name": "News"
      },
      "region": "EUR",
      "delay": 1,
      "universe": "TOP2500",
      "type": "MATRIX",
      "dateCoverage": 1,
      "coverage": 0.5102,
      "userCount": 1,
      "alphaCount": 2,
      "pyramidMultiplier": 1.5,
      "themes": []
    },
    {
      "id": "event_transcript_sentiment_score",
      "description": "A composite score reflecting the overall sentiment of an event transcript.",
      "dataset": {
        "id": "news21",
        "name": "Macro Economic Event Data"
      },
      "category": {
        "id": "news",
        "name": "News"
      },
      "subcategory": {
        "id": "news-news",
        "name": "News"
      },
      "region": "EUR",
      "delay": 1,
      "universe": "TOP2500",
      "type": "MATRIX",
      "dateCoverage": 1,
      "coverage": 0.5102,
      "userCount": 0,
      "alphaCount": 0,
      "pyramidMultiplier": 1.5,
      "themes": []
    },
    {
      "id": "event_transcript_total_word_count",
      "description": "The total number of words or tokens in an event transcript.",
      "dataset": {
        "id": "news21",
        "name": "Macro Economic Event Data"
      },
      "category": {
        "id": "news",
        "name": "News"
      },
      "subcategory": {
        "id": "news-news",
        "name": "News"
      },
      "region": "EUR",
      "delay": 1,
      "universe": "TOP2500",
      "type": "MATRIX",
      "dateCoverage": 1,
      "coverage": 0.5102,
      "userCount": 1,
      "alphaCount": 1,
      "pyramidMultiplier": 1.5,
      "themes": []
    },
    {
      "id": "negative_sentiment_score_1",
      "description": "A numerical score representing the negative sentiment in the transcript (version 1).",
      "dataset": {
        "id": "news21",
        "name": "Macro Economic Event Data"
      },
      "category": {
        "id": "news",
        "name": "News"
      },
      "subcategory": {
        "id": "news-news",
        "name": "News"
      },
      "region": "EUR",
      "delay": 1,
      "universe": "TOP2500",
      "type": "VECTOR",
      "dateCoverage": 1,
      "coverage": 0.4169,
      "userCount": 5,
      "alphaCount": 5,
      "pyramidMultiplier": 1.5,
      "themes": []
    },
    {
      "id": "negative_word_count_1",
      "description": "The number of negative words or phrases detected in the transcript (version 1).",
      "dataset": {
        "id": "news21",
        "name": "Macro Economic Event Data"
      },
      "category": {
        "id": "news",
        "name": "News"
      },
      "subcategory": {
        "id": "news-news",
        "name": "News"
      },
      "region": "EUR",
      "delay": 1,
      "universe": "TOP2500",
      "type": "VECTOR",
      "dateCoverage": 1,
      "coverage": 0.4169,
      "userCount": 0,
      "alphaCount": 0,
      "pyramidMultiplier": 1.5,
      "themes": []
    },
    {
      "id": "next_corporate_presentation_date",
      "description": "The scheduled date of the next corporate presentation event.",
      "dataset": {
        "id": "news21",
        "name": "Macro Economic Event Data"
      },
      "category": {
        "id": "news",
        "name": "News"
      },
      "subcategory": {
        "id": "news-news",
        "name": "News"
      },
      "region": "EUR",
      "delay": 1,
      "universe": "TOP2500",
      "type": "MATRIX",
      "dateCoverage": 1,
      "coverage": 0.1616,
      "userCount": 1,
      "alphaCount": 1,
      "pyramidMultiplier": 1.5,
      "themes": []
    },
    {
      "id": "next_earnings_call_date",
      "description": "The scheduled date of the next earnings conference call event.",
      "dataset": {
        "id": "news21",
        "name": "Macro Economic Event Data"
      },
      "category": {
        "id": "news",
        "name": "News"
      },
      "subcategory": {
        "id": "news-news",
        "name": "News"
      },
      "region": "EUR",
      "delay": 1,
      "universe": "TOP2500",
      "type": "MATRIX",
      "dateCoverage": 1,
      "coverage": 0.5413,
      "userCount": 3,
      "alphaCount": 3,
      "pyramidMultiplier": 1.5,
      "themes": []
    },
    {
      "id": "next_earnings_estimate_date",
      "description": "The scheduled date for the next estimated earnings release.",
      "dataset": {
        "id": "news21",
        "name": "Macro Economic Event Data"
      },
      "category": {
        "id": "news",
        "name": "News"
      },
      "subcategory": {
        "id": "news-news",
        "name": "News"
      },
      "region": "EUR",
      "delay": 1,
      "universe": "TOP2500",
      "type": "MATRIX",
      "dateCoverage": 1,
      "coverage": 0.54,
      "userCount": 2,
      "alphaCount": 2,
      "pyramidMultiplier": 1.5,
      "themes": []
    },
    {
      "id": "next_ex_dividend_event_date",
      "description": "The scheduled date of the next ex-dividend event for the security.",
      "dataset": {
        "id": "news21",
        "name": "Macro Economic Event Data"
      },
      "category": {
        "id": "news",
        "name": "News"
      },
      "subcategory": {
        "id": "news-news",
        "name": "News"
      },
      "region": "EUR",
      "delay": 1,
      "universe": "TOP2500",
      "type": "MATRIX",
      "dateCoverage": 1,
      "coverage": 0.4228,
      "userCount": 9,
      "alphaCount": 9,
      "pyramidMultiplier": 1.5,
      "themes": []
    },
    {
      "id": "next_shareholder_meeting_date",
      "description": "The scheduled date of the next annual shareholder meeting.",
      "dataset": {
        "id": "news21",
        "name": "Macro Economic Event Data"
      },
      "category": {
        "id": "news",
        "name": "News"
      },
      "subcategory": {
        "id": "news-news",
        "name": "News"
      },
      "region": "EUR",
      "delay": 1,
      "universe": "TOP2500",
      "type": "MATRIX",
      "dateCoverage": 1,
      "coverage": 0.4903,
      "userCount": 5,
      "alphaCount": 5,
      "pyramidMultiplier": 1.5,
      "themes": []
    },
    {
      "id": "nws21_event_freq",
      "description": "number of events.",
      "dataset": {
        "id": "news21",
        "name": "Macro Economic Event Data"
      },
      "category": {
        "id": "news",
        "name": "News"
      },
      "subcategory": {
        "id": "news-news",
        "name": "News"
      },
      "region": "EUR",
      "delay": 1,
      "universe": "TOP2500",
      "type": "MATRIX",
      "dateCoverage": 1,
      "coverage": 0.5102,
      "userCount": 0,
      "alphaCount": 0,
      "pyramidMultiplier": 1.5,
      "themes": []
    },
    {
      "id": "nws21_neg_sc",
      "description": "number of negative words/number of all words.",
      "dataset": {
        "id": "news21",
        "name": "Macro Economic Event Data"
      },
      "category": {
        "id": "news",
        "name": "News"
      },
      "subcategory": {
        "id": "news-news",
        "name": "News"
      },
      "region": "EUR",
      "delay": 1,
      "universe": "TOP2500",
      "type": "MATRIX",
      "dateCoverage": 1,
      "coverage": 0.5102,
      "userCount": 1,
      "alphaCount": 1,
      "pyramidMultiplier": 1.5,
      "themes": []
    },
    {
      "id": "nws21_pos_sc",
      "description": "number of positive words/number of all words.",
      "dataset": {
        "id": "news21",
        "name": "Macro Economic Event Data"
      },
      "category": {
        "id": "news",
        "name": "News"
      },
      "subcategory": {
        "id": "news-news",
        "name": "News"
      },
      "region": "EUR",
      "delay": 1,
      "universe": "TOP2500",
      "type": "MATRIX",
      "dateCoverage": 1,
      "coverage": 0.5102,
      "userCount": 6,
      "alphaCount": 7,
      "pyramidMultiplier": 1.5,
      "themes": []
    },
    {
      "id": "nws21_qerf_gen",
      "description": "number of negative words.",
      "dataset": {
        "id": "news21",
        "name": "Macro Economic Event Data"
      },
      "category": {
        "id": "news",
        "name": "News"
      },
      "subcategory": {
        "id": "news-news",
        "name": "News"
      },
      "region": "EUR",
      "delay": 1,
      "universe": "TOP2500",
      "type": "MATRIX",
      "dateCoverage": 1,
      "coverage": 0.5102,
      "userCount": 1,
      "alphaCount": 1,
      "pyramidMultiplier": 1.5,
      "themes": []
    },
    {
      "id": "nws21_qerf_sop",
      "description": "number of positive words.",
      "dataset": {
        "id": "news21",
        "name": "Macro Economic Event Data"
      },
      "category": {
        "id": "news",
        "name": "News"
      },
      "subcategory": {
        "id": "news-news",
        "name": "News"
      },
      "region": "EUR",
      "delay": 1,
      "universe": "TOP2500",
      "type": "MATRIX",
      "dateCoverage": 1,
      "coverage": 0.5102,
      "userCount": 3,
      "alphaCount": 3,
      "pyramidMultiplier": 1.5,
      "themes": []
    },
    {
      "id": "nws21_tone_tone_sc",
      "description": "(number of positive words - number of negative words)/(number of positive words + number of negative words)",
      "dataset": {
        "id": "news21",
        "name": "Macro Economic Event Data"
      },
      "category": {
        "id": "news",
        "name": "News"
      },
      "subcategory": {
        "id": "news-news",
        "name": "News"
      },
      "region": "EUR",
      "delay": 1,
      "universe": "TOP2500",
      "type": "MATRIX",
      "dateCoverage": 1,
      "coverage": 0.5102,
      "userCount": 1,
      "alphaCount": 1,
      "pyramidMultiplier": 1.5,
      "themes": []
    },
    {
      "id": "overall_tone_score_1",
      "description": "A numerical score representing the overall sentiment or tone of the transcript (version 1).",
      "dataset": {
        "id": "news21",
        "name": "Macro Economic Event Data"
      },
      "category": {
        "id": "news",
        "name": "News"
      },
      "subcategory": {
        "id": "news-news",
        "name": "News"
      },
      "region": "EUR",
      "delay": 1,
      "universe": "TOP2500",
      "type": "VECTOR",
      "dateCoverage": 1,
      "coverage": 0.4169,
      "userCount": 0,
      "alphaCount": 0,
      "pyramidMultiplier": 1.5,
      "themes": []
    },
    {
      "id": "positive_sentiment_score_1",
      "description": "A numerical score representing the positive sentiment in the transcript (version 1).",
      "dataset": {
        "id": "news21",
        "name": "Macro Economic Event Data"
      },
      "category": {
        "id": "news",
        "name": "News"
      },
      "subcategory": {
        "id": "news-news",
        "name": "News"
      },
      "region": "EUR",
      "delay": 1,
      "universe": "TOP2500",
      "type": "VECTOR",
      "dateCoverage": 1,
      "coverage": 0.4169,
      "userCount": 1,
      "alphaCount": 3,
      "pyramidMultiplier": 1.5,
      "themes": []
    },
    {
      "id": "positive_word_count_1",
      "description": "The number of positive words or phrases detected in the transcript (version 1).",
      "dataset": {
        "id": "news21",
        "name": "Macro Economic Event Data"
      },
      "category": {
        "id": "news",
        "name": "News"
      },
      "subcategory": {
        "id": "news-news",
        "name": "News"
      },
      "region": "EUR",
      "delay": 1,
      "universe": "TOP2500",
      "type": "VECTOR",
      "dateCoverage": 1,
      "coverage": 0.4169,
      "userCount": 1,
      "alphaCount": 1,
      "pyramidMultiplier": 1.5,
      "themes": []
    },
    {
      "id": "previous_corporate_presentation_date",
      "description": "The date of the most recent past corporate presentation event.",
      "dataset": {
        "id": "news21",
        "name": "Macro Economic Event Data"
      },
      "category": {
        "id": "news",
        "name": "News"
      },
      "subcategory": {
        "id": "news-news",
        "name": "News"
      },
      "region": "EUR",
      "delay": 1,
      "universe": "TOP2500",
      "type": "MATRIX",
      "dateCoverage": 1,
      "coverage": 0.3792,
      "userCount": 1,
      "alphaCount": 1,
      "pyramidMultiplier": 1.5,
      "themes": []
    },
    {
      "id": "previous_earnings_call_date",
      "description": "The date of the most recent past earnings conference call event.",
      "dataset": {
        "id": "news21",
        "name": "Macro Economic Event Data"
      },
      "category": {
        "id": "news",
        "name": "News"
      },
      "subcategory": {
        "id": "news-news",
        "name": "News"
      },
      "region": "EUR",
      "delay": 1,
      "universe": "TOP2500",
      "type": "MATRIX",
      "dateCoverage": 1,
      "coverage": 0.769,
      "userCount": 10,
      "alphaCount": 10,
      "pyramidMultiplier": 1.5,
      "themes": []
    },
    {
      "id": "previous_ex_dividend_event_date",
      "description": "The date of the most recent past ex-dividend event for the security.",
      "dataset": {
        "id": "news21",
        "name": "Macro Economic Event Data"
      },
      "category": {
        "id": "news",
        "name": "News"
      },
      "subcategory": {
        "id": "news-news",
        "name": "News"
      },
      "region": "EUR",
      "delay": 1,
      "universe": "TOP2500",
      "type": "MATRIX",
      "dateCoverage": 1,
      "coverage": 0.5654,
      "userCount": 46,
      "alphaCount": 94,
      "pyramidMultiplier": 1.5,
      "themes": []
    },
    {
      "id": "previous_sales_statement_date",
      "description": "The date of the most recent prior sales or trading statement release.",
      "dataset": {
        "id": "news21",
        "name": "Macro Economic Event Data"
      },
      "category": {
        "id": "news",
        "name": "News"
      },
      "subcategory": {
        "id": "news-news",
        "name": "News"
      },
      "region": "EUR",
      "delay": 1,
      "universe": "TOP2500",
      "type": "MATRIX",
      "dateCoverage": 1,
      "coverage": 0.298,
      "userCount": 4,
      "alphaCount": 4,
      "pyramidMultiplier": 1.5,
      "themes": []
    },
    {
      "id": "previous_shareholder_meeting_date",
      "description": "The date of the most recent past annual shareholder meeting.",
      "dataset": {
        "id": "news21",
        "name": "Macro Economic Event Data"
      },
      "category": {
        "id": "news",
        "name": "News"
      },
      "subcategory": {
        "id": "news-news",
        "name": "News"
      },
      "region": "EUR",
      "delay": 1,
      "universe": "TOP2500",
      "type": "MATRIX",
      "dateCoverage": 1,
      "coverage": 0.5076,
      "userCount": 42,
      "alphaCount": 72,
      "pyramidMultiplier": 1.5,
      "themes": []
    },
    {
      "id": "transcript_version_label_1",
      "description": "The version or editing status of the transcript (version 1).",
      "dataset": {
        "id": "news21",
        "name": "Macro Economic Event Data"
      },
      "category": {
        "id": "news",
        "name": "News"
      },
      "subcategory": {
        "id": "news-news",
        "name": "News"
      },
      "region": "EUR",
      "delay": 1,
      "universe": "TOP2500",
      "type": "VECTOR",
      "dateCoverage": 1,
      "coverage": 0.4169,
      "userCount": 2,
      "alphaCount": 2,
      "pyramidMultiplier": 1.5,
      "themes": []
    }
  ]
}